signalhandlers/__init__.py
signalhandlers/sigs.py
signalhandlers-0.0.1.dist-info/METADATA
signalhandlers-0.0.1.dist-info/WHEEL
signalhandlers-0.0.1.dist-info/top_level.txt
signalhandlers-0.0.1.dist-info/RECORD
