Metadata-Version: 2.1
Name: signalhandlers
Version: 0.0.1
Summary: Signal handlers.
Author-email: Jason Wilkes <notarealdeveloper@gmail.com>
Project-URL: Homepage, https://github.com/notarealdeveloper/signalhandlers
